optimihost/__init__.py
optimihost/api_client.py
optimihost/constants.py
optimihost/exceptions.py
optimihost/responses.py
optimihost/api/__init__.py
optimihost/api/base.py
optimihost/api/locations.py
optimihost/api/nests.py
optimihost/api/nodes.py
optimihost/api/servers.py
optimihost/api/user.py
optimihost/api/client/__init__.py
optimihost/api/client/client_api.py
optimihost/api/client/account/__init__.py
optimihost/api/client/account/base.py
optimihost/api/client/servers/__init__.py
optimihost/api/client/servers/backups.py
optimihost/api/client/servers/base.py
optimihost/api/client/servers/databases.py
optimihost/api/client/servers/files.py
optimihost/api/client/servers/network.py
optimihost/api/client/servers/schedules.py
optimihost/api/client/servers/settings.py
optimihost/api/client/servers/startup.py
optimihost/api/client/servers/users.py
optimihost-0.2.0.dist-info/licenses/LICENSE
optimihost-0.2.0.dist-info/METADATA
optimihost-0.2.0.dist-info/WHEEL
optimihost-0.2.0.dist-info/top_level.txt
optimihost-0.2.0.dist-info/RECORD
