Metadata-Version: 2.4
Name: optimihost
Version: 0.2.0
Summary: API For optimihost
Home-page: https://github.com/iamkubi/pydactyl
Author: OptimiHost and EAMCVD
Author-email: info@optimihost.com
Project-URL: Website, https://developer.optimihost.com/
Project-URL: Source, https://github.com/iamkubi/pydactyl
Classifier: Programming Language :: Python :: 3
Classifier: License :: OSI Approved :: MIT License
Classifier: Natural Language :: English
Classifier: Operating System :: OS Independent
Requires-Python: >=3.4
License-File: LICENSE
Requires-Dist: requests>=2.21.0
Dynamic: author
Dynamic: author-email
Dynamic: classifier
Dynamic: description
Dynamic: description-content-type
Dynamic: home-page
Dynamic: license-file
Dynamic: project-url
Dynamic: requires-dist
Dynamic: requires-python
Dynamic: summary
